runana/__init__.py
runana/analyse.py
runana/analyse_pandas.py
runana/input_file_handling.py
runana/matplotlib_managers.py
runana/read_numbers.py
runana/run.py
runana-0.1.7.dist-info/LICENSE
runana-0.1.7.dist-info/METADATA
runana-0.1.7.dist-info/WHEEL
runana-0.1.7.dist-info/top_level.txt
runana-0.1.7.dist-info/RECORD
