Metadata-Version: 2.1
Name: runana
Version: 0.1.7
Summary: UNKNOWN
Home-page: UNKNOWN
Author: Jens Svensmark
Author-email: jenssss@uec.ac.jp
License: UNKNOWN
Keywords: run analyse
Platform: UNKNOWN
Classifier: Development Status :: 2 - Pre-Alpha
Classifier: Topic :: Utilities
License-File: LICENSE
